mreddata/__init__.py
mreddata/datatools.py
mreddata/hdf5data.py
mreddata/pkldata.py
mreddata/plottools.py
mreddata/txtdata.py
mreddata-0.3.87.dist-info/LICENSE
mreddata-0.3.87.dist-info/METADATA
mreddata-0.3.87.dist-info/WHEEL
mreddata-0.3.87.dist-info/top_level.txt
mreddata-0.3.87.dist-info/RECORD
