Metadata-Version: 2.1
Name: mreddata
Version: 0.3.87
Summary: A colletion of data and visualization tools for MRED/HDF5
Home-page: https://github.com/matthew-breeding/mreddata
Author: Matthew Breeding
Author-email: matthew.l.breeding@vanderbilt.edu
License: UNKNOWN
Download-URL: https://pypi.org/project/mreddata
Platform: UNKNOWN
Classifier: Programming Language :: Python :: 3
Classifier: License :: OSI Approved :: MIT License
Classifier: Operating System :: OS Independent
Requires-Python: >=3.6
Requires-Dist: h5py (>=2.10.0)
Requires-Dist: matplotlib (>=3.1.1)
Requires-Dist: numpy (>=1.17.1)
Requires-Dist: pandas (>=0.25.1)
